cc_dump/__init__.py
cc_dump/__main__.py
cc_dump/analysis.py
cc_dump/cli.py
cc_dump/colors.py
cc_dump/db_queries.py
cc_dump/formatting.py
cc_dump/hot_reload.py
cc_dump/palette.py
cc_dump/proxy.py
cc_dump/router.py
cc_dump/schema.py
cc_dump/store.py
cc_dump/tui/__init__.py
cc_dump/tui/app.py
cc_dump/tui/custom_footer.py
cc_dump/tui/event_handlers.py
cc_dump/tui/panel_renderers.py
cc_dump/tui/protocols.py
cc_dump/tui/rendering.py
cc_dump/tui/styles.css
cc_dump/tui/widget_factory.py
cc_dump/tui/widgets.py
cc_dump-0.2.0.dist-info/METADATA
cc_dump-0.2.0.dist-info/WHEEL
cc_dump-0.2.0.dist-info/entry_points.txt
cc_dump-0.2.0.dist-info/licenses/LICENSE
cc_dump-0.2.0.dist-info/RECORD
