Metadata-Version: 2.4
Name: cc-dump
Version: 0.2.0
Summary: Transparent HTTP proxy for monitoring Claude Code API traffic with TUI
Project-URL: Homepage, https://github.com/brandon-fryslie/cc-dump
Project-URL: Repository, https://github.com/brandon-fryslie/cc-dump
Project-URL: Issues, https://github.com/brandon-fryslie/cc-dump/issues
Author-email: Brandon Fryslie <brandon@fryslie.com>
License: MIT
License-File: LICENSE
Keywords: anthropic,api,claude,debugging,proxy,tui
Classifier: Development Status :: 4 - Beta
Classifier: Environment :: Console
Classifier: Intended Audience :: Developers
Classifier: License :: OSI Approved :: MIT License
Classifier: Programming Language :: Python :: 3
Classifier: Programming Language :: Python :: 3.10
Classifier: Programming Language :: Python :: 3.11
Classifier: Programming Language :: Python :: 3.12
Classifier: Topic :: Software Development :: Debuggers
Classifier: Topic :: Utilities
Requires-Python: >=3.10
Requires-Dist: textual>=0.80.0
